[
  {
    "id": "r1001",
    "title": "沁园春·雪",
    "content": [
      "北国风光，千里冰封，万里雪飘。",
      "望长城内外，惟余莽莽；大河上下，顿失滔滔。",
      "山舞银蛇，原驰蜡象，欲与天公试比高。",
      "须晴日，看红装素裹，分外妖娆。",
      "江山如此多娇，引无数英雄竞折腰。",
      "惜秦皇汉武，略输文采；唐宗宋祖，稍逊风骚。",
      "一代天骄，成吉思汗，只识弯弓射大雕。",
      "俱往矣，数风流人物，还看今朝。"
    ],
    "poet": "毛泽东",
    "dynasty": "近现代",
    "theme": ["励志", "山水"],
    "likedCount": 0
  },
  {
    "id": "r1002",
    "title": "沁园春·长沙",
    "content": [
      "独立寒秋，湘江北去，橘子洲头。",
      "看万山红遍，层林尽染；漫江碧透，百舸争流。",
      "鹰击长空，鱼翔浅底，万类霜天竞自由。",
      "怅寥廓，问苍茫大地，谁主沉浮？",
      "携来百侣曾游，忆往昔峥嵘岁月稠。",
      "恰同学少年，风华正茂；书生意气，挥斥方遒。",
      "指点江山，激扬文字，粪土当年万户侯。",
      "曾记否，到中流击水，浪遏飞舟？"
    ],
    "poet": "毛泽东",
    "dynasty": "近现代",
    "theme": ["励志", "友情", "山水"],
    "likedCount": 0
  },
  {
    "id": "r1003",
    "title": "忆秦娥·娄山关",
    "content": [
      "西风烈，长空雁叫霜晨月。",
      "霜晨月，马蹄声碎，喇叭声咽。",
      "雄关漫道真如铁，而今迈步从头越。",
      "从头越，苍山如海，残阳如血。"
    ],
    "poet": "毛泽东",
    "dynasty": "近现代",
    "theme": ["励志", "离别"],
    "likedCount": 0
  },
  {
    "id": "r1004",
    "title": "七律·长征",
    "content": [
      "红军不怕远征难，万水千山只等闲。",
      "五岭逶迤腾细浪，乌蒙磅礴走泥丸。",
      "金沙水拍云崖暖，大渡桥横铁索寒。",
      "更喜岷山千里雪，三军过后尽开颜。"
    ],
    "poet": "毛泽东",
    "dynasty": "近现代",
    "theme": ["励志", "山水"],
    "likedCount": 0
  },
  {
    "id": "r1005",
    "title": "七律·人民解放军占领南京",
    "content": [
      "钟山风雨起苍黄，百万雄师过大江。",
      "虎踞龙盘今胜昔，天翻地覆慨而慷。",
      "宜将剩勇追穷寇，不可沽名学霸王。",
      "天若有情天亦老，人间正道是沧桑。"
    ],
    "poet": "毛泽东",
    "dynasty": "近现代",
    "theme": ["励志"],
    "likedCount": 0
  },
  {
    "id": "r1006",
    "title": "七律·到韶山",
    "content": [
      "别梦依稀咒逝川，故园三十二年前。",
      "红旗卷起农奴戟，黑手高悬霸主鞭。",
      "为有牺牲多壮志，敢教日月换新天。",
      "喜看稻菽千重浪，遍地英雄下夕烟。"
    ],
    "poet": "毛泽东",
    "dynasty": "近现代",
    "theme": ["励志", "思乡"],
    "likedCount": 0
  },
  {
    "id": "r1007",
    "title": "七律·和柳亚子先生",
    "content": [
      "饮茶粤海未能忘，索句渝州叶正黄。",
      "三十一年还旧国，落花时节读华章。",
      "牢骚太盛防肠断，风物长宜放眼量。",
      "莫道昆明池水浅，观鱼胜过富春江。"
    ],
    "poet": "毛泽东",
    "dynasty": "近现代",
    "theme": ["友情", "励志"],
    "likedCount": 0
  },
  {
    "id": "r1008",
    "title": "七律·和郭沫若同志",
    "content": [
      "一从大地起风雷，便有精生白骨堆。",
      "僧是愚氓犹可训，妖为鬼蜮必成灾。",
      "金猴奋起千钧棒，玉宇澄清万里埃。",
      "今日欢呼孙大圣，只缘妖雾又重来。"
    ],
    "poet": "毛泽东",
    "dynasty": "近现代",
    "theme": ["励志", "友情"],
    "likedCount": 0
  },
  {
    "id": "r1009",
    "title": "清平乐·六盘山",
    "content": [
      "天高云淡，望断南飞雁。",
      "不到长城非好汉，屈指行程二万。",
      "六盘山上高峰，红旗漫卷西风。",
      "今日长缨在手，何时缚住苍龙？"
    ],
    "poet": "毛泽东",
    "dynasty": "近现代",
    "theme": ["励志", "山水"],
    "likedCount": 0
  },
  {
    "id": "r1010",
    "title": "清平乐·会昌",
    "content": [
      "东方欲晓，莫道君行早。",
      "踏遍青山人未老，风景这边独好。",
      "会昌城外高峰，颠连直接东溟。",
      "战士指看南粤，更加郁郁葱葱。"
    ],
    "poet": "毛泽东",
    "dynasty": "近现代",
    "theme": ["励志", "山水"],
    "likedCount": 0
  },
  {
    "id": "r1011",
    "title": "菩萨蛮·大柏地",
    "content": [
      "赤橙黄绿青蓝紫，谁持彩练当空舞。",
      "雨后复斜阳，关山阵阵苍。",
      "当年鏖战急，弹洞前村壁。",
      "装点此关山，今朝更好看。"
    ],
    "poet": "毛泽东",
    "dynasty": "近现代",
    "theme": ["励志", "山水"],
    "likedCount": 0
  },
  {
    "id": "r1012",
    "title": "渔家傲·反第一次大围剿",
    "content": [
      "万木霜天红烂漫，天兵怒气冲霄汉。",
      "雾满龙冈千嶂暗，齐声唤，前头捉了张辉瓒。",
      "二十万军重入赣，风烟滚滚来天半。",
      "唤起工农千百万，同心干，不周山下红旗乱。"
    ],
    "poet": "毛泽东",
    "dynasty": "近现代",
    "theme": ["励志"],
    "likedCount": 0
  },
  {
    "id": "r1013",
    "title": "渔家傲·反第二次大围剿",
    "content": [
      "白云山头云欲立，白云山下呼声急，枯木朽株齐努力。",
      "枪林逼，飞将军自重霄入。",
      "七百里驱十五日，赣水苍茫闽山碧，横扫千军如卷席。",
      "有人泣，为营步步嗟何及！"
    ],
    "poet": "毛泽东",
    "dynasty": "近现代",
    "theme": ["励志"],
    "likedCount": 0
  },
  {
    "id": "r1014",
    "title": "渔家傲·反第三次大围剿",
    "content": [
      "英勇红军凭肉搏，红旗翻处白旗没。",
      "地动天摇风雨跃，雷霆落，今日梁魁应活捉。"
    ],
    "poet": "毛泽东",
    "dynasty": "近现代",
    "theme": ["励志"],
    "likedCount": 0
  },
  {
    "id": "r1015",
    "title": "采桑子·重阳",
    "content": [
      "人生易老天难老，岁岁重阳。",
      "今又重阳，战地黄花分外香。",
      "一年一度秋风劲，不似春光。",
      "胜似春光，寥廓江天万里霜。"
    ],
    "poet": "毛泽东",
    "dynasty": "近现代",
    "theme": ["励志", "离别"],
    "likedCount": 0
  },
  {
    "id": "r1016",
    "title": "浪淘沙·北戴河",
    "content": [
      "大雨落幽燕，白浪滔天。",
      "秦皇岛外打鱼船，一片汪洋都不见。",
      "知向谁边？",
      "往事越千年。",
      "魏武挥鞭，东临碣石有遗篇。",
      "萧瑟秋风今又是，换了人间。"
    ],
    "poet": "毛泽东",
    "dynasty": "近现代",
    "theme": ["山水", "励志"],
    "likedCount": 0
  },
  {
    "id": "r1017",
    "title": "水调歌头·重上井冈山",
    "content": [
      "久有凌云志，重上井冈山。",
      "千里来寻故地，旧貌变新颜。",
      "到处莺歌燕舞，更有潺潺流水，高路入云端。",
      "过了黄洋界，险处不须看。",
      "风雷动，旌旗奋，是人寰。",
      "三十八年过去，弹指一挥间。",
      "可上九天揽月，可下五洋捉鳖，谈笑凯歌还。",
      "世上无难事，只要肯登攀。"
    ],
    "poet": "毛泽东",
    "dynasty": "近现代",
    "theme": ["励志", "思乡", "山水"],
    "likedCount": 0
  },
  {
    "id": "r1018",
    "title": "卜算子·咏梅",
    "content": [
      "风雨送春归，飞雪迎春到。",
      "已是悬崖百丈冰，犹有花枝俏。",
      "俏也不争春，只把春来报。",
      "待到山花烂漫时，她在丛中笑。"
    ],
    "poet": "毛泽东",
    "dynasty": "近现代",
    "theme": ["励志"],
    "likedCount": 0
  },
  {
    "id": "r1019",
    "title": "七绝·为李进同志题所摄庐山仙人洞照",
    "content": [
      "暮色苍茫看劲松，乱云飞渡仍从容。",
      "天生一个仙人洞，无限风光在险峰。"
    ],
    "poet": "毛泽东",
    "dynasty": "近现代",
    "theme": ["山水", "励志"],
    "likedCount": 0
  },
  {
    "id": "r1020",
    "title": "七律·吊罗荣桓同志",
    "content": [
      "记得当年草上飞，红军队里每相随。",
      "长征不是难堪日，战锦方为大问题。",
      "斥鷃每闻欺大鸟，昆鸡长笑老鹰非。",
      "君今不幸离人世，国有疑难可问谁？"
    ],
    "poet": "毛泽东",
    "dynasty": "近现代",
    "theme": ["友情", "励志"],
    "likedCount": 0
  },

  {
    "id": "r2001",
    "title": "木兰花令·拟古决绝词",
    "content": [
      "人生若只如初见，何事秋风悲画扇。",
      "等闲变却故人心，却道故人心易变。",
      "骊山语罢清宵半，泪雨霖铃终不怨。",
      "何如薄幸锦衣郎，比翼连枝当日愿。"
    ],
    "poet": "纳兰性德",
    "dynasty": "清代",
    "theme": ["爱情", "离别"],
    "likedCount": 0
  },
  {
    "id": "r2002",
    "title": "木兰花·人生若只如初见",
    "content": [
      "人生若只如初见，何事秋风悲画扇。",
      "等闲变却故人心，却道故人心易变。",
      "骊山语罢清宵半，泪雨霖铃终不怨。",
      "何如薄幸锦衣郎，比翼连枝当日愿。"
    ],
    "poet": "纳兰性德",
    "dynasty": "清代",
    "theme": ["爱情", "离别"],
    "likedCount": 0
  },
  {
    "id": "r2003",
    "title": "浣溪沙·谁念西风独自凉",
    "content": [
      "谁念西风独自凉，萧萧黄叶闭疏窗，沉思往事立残阳。",
      "被酒莫惊春睡重，赌书消得泼茶香，当时只道是寻常。"
    ],
    "poet": "纳兰性德",
    "dynasty": "清代",
    "theme": ["爱情", "离别"],
    "likedCount": 0
  },
  {
    "id": "r2004",
    "title": "鹧鸪天·晚日寒鸦一片愁",
    "content": [
      "晚日寒鸦一片愁，柳塘新绿却温柔。",
      "若教眼底无离恨，不信人间有白头。",
      "肠已断，泪难收，相思重上小红楼。",
      "情知已被山遮断，频倚阑干不自由。"
    ],
    "poet": "纳兰性德",
    "dynasty": "清代",
    "theme": ["爱情", "思乡"],
    "likedCount": 0
  },
  {
    "id": "r2005",
    "title": "生查子·惆怅彩云飞",
    "content": [
      "惆怅彩云飞，碧落知何许。",
      "不见合欢花，空倚相思树。",
      "总是别时情，那待分明语。",
      "判得最长宵，数尽厌厌雨。"
    ],
    "poet": "纳兰性德",
    "dynasty": "清代",
    "theme": ["爱情"],
    "likedCount": 0
  },
  {
    "id": "r2006",
    "title": "采桑子·而今才道当时错",
    "content": [
      "而今才道当时错，心绪凄迷。",
      "红泪偷垂，满眼春风百事非。",
      "情知此后来无计，强说欢期。",
      "一别如斯，落尽梨花月又西。"
    ],
    "poet": "纳兰性德",
    "dynasty": "清代",
    "theme": ["爱情", "离别"],
    "likedCount": 0
  },
  {
    "id": "r2007",
    "title": "蝶恋花·辛苦最怜天上月",
    "content": [
      "辛苦最怜天上月，一昔如环，昔昔都成玦。",
      "若似月轮终皎洁，不辞冰雪为卿热。",
      "无那尘缘容易绝，燕子依然，软踏帘钩说。",
      "唱罢秋坟愁未歇，春丛认取双栖蝶。"
    ],
    "poet": "纳兰性德",
    "dynasty": "清代",
    "theme": ["爱情"],
    "likedCount": 0
  },
  {
    "id": "r2008",
    "title": "菩萨蛮·新寒中酒敲窗雨",
    "content": [
      "新寒中酒敲窗雨，残香细袅秋情绪。",
      "才道莫伤神，青衫湿一痕。",
      "无聊成独卧，弹指韶光过。",
      "记得别伊时，桃花柳万丝。"
    ],
    "poet": "纳兰性德",
    "dynasty": "清代",
    "theme": ["离别", "思乡"],
    "likedCount": 0
  },
  {
    "id": "r2009",
    "title": "南乡子·为亡妇题照",
    "content": [
      "泪咽却无声，只向从前悔薄情。",
      "凭仗丹青重省识，盈盈，一片伤心画不成。",
      "别语忒分明，午夜鹣鹣梦早醒。",
      "卿自早醒侬自梦，更更，泣尽风檐夜雨铃。"
    ],
    "poet": "纳兰性德",
    "dynasty": "清代",
    "theme": ["爱情", "离别"],
    "likedCount": 0
  },
  {
    "id": "r2010",
    "title": "梦江南·昏鸦尽",
    "content": [
      "昏鸦尽，小立恨因谁？",
      "急雪乍翻香阁絮，轻风吹到胆瓶梅，心字已成灰。"
    ],
    "poet": "纳兰性德",
    "dynasty": "清代",
    "theme": ["爱情", "离别"],
    "likedCount": 0
  },

  {
    "id": "r3001",
    "title": "静夜思",
    "content": [
      "床前明月光，疑是地上霜。",
      "举头望明月，低头思故乡。"
    ],
    "poet": "李白",
    "dynasty": "唐代",
    "theme": ["思乡", "山水"],
    "likedCount": 0
  },
  {
    "id": "r3002",
    "title": "将进酒",
    "content": [
      "君不见黄河之水天上来，奔流到海不复回。",
      "君不见高堂明镜悲白发，朝如青丝暮成雪。",
      "人生得意须尽欢，莫使金樽空对月。",
      "天生我材必有用，千金散尽还复来。",
      "烹羊宰牛且为乐，会须一饮三百杯。",
      "岑夫子，丹丘生，将进酒，君莫停。",
      "与君歌一曲，请君为我倾耳听。",
      "钟鼓馔玉不足贵，但愿长醉不愿醒。",
      "古来圣贤皆寂寞，惟有饮者留其名。",
      "陈王昔时宴平乐，斗酒十千恣欢谑。",
      "主人何为言少钱，径须沽取对君酌。",
      "五花马，千金裘，呼儿将出换美酒，与尔同销万古愁。"
    ],
    "poet": "李白",
    "dynasty": "唐代",
    "theme": ["励志", "山水"],
    "likedCount": 0
  },
  {
    "id": "r3003",
    "title": "登鹳雀楼",
    "content": [
      "白日依山尽，黄河入海流。",
      "欲穷千里目，更上一层楼。"
    ],
    "poet": "王之涣",
    "dynasty": "唐代",
    "theme": ["励志", "山水"],
    "likedCount": 0
  },
  {
    "id": "r3004",
    "title": "春望",
    "content": [
      "国破山河在，城春草木深。",
      "感时花溅泪，恨别鸟惊心。",
      "烽火连三月，家书抵万金。",
      "白头搔更短，浑欲不胜簪。"
    ],
    "poet": "杜甫",
    "dynasty": "唐代",
    "theme": ["离别", "山水"],
    "likedCount": 0
  },
  {
    "id": "r3005",
    "title": "登高",
    "content": [
      "风急天高猿啸哀，渚清沙白鸟飞回。",
      "无边落木萧萧下，不尽长江滚滚来。",
      "万里悲秋常作客，百年多病独登台。",
      "艰难苦恨繁霜鬓，潦倒新停浊酒杯。"
    ],
    "poet": "杜甫",
    "dynasty": "唐代",
    "theme": ["山水", "励志"],
    "likedCount": 0
  },
  {
    "id": "r3006",
    "title": "泊秦淮",
    "content": [
      "烟笼寒水月笼沙，夜泊秦淮近酒家。",
      "商女不知亡国恨，隔江犹唱后庭花。"
    ],
    "poet": "杜牧",
    "dynasty": "唐代",
    "theme": ["离别", "山水"],
    "likedCount": 0
  },
  {
    "id": "r3007",
    "title": "秋夕",
    "content": [
      "银烛秋光冷画屏，轻罗小扇扑流萤。",
      "天阶夜色凉如水，卧看牵牛织女星。"
    ],
    "poet": "杜牧",
    "dynasty": "唐代",
    "theme": ["爱情"],
    "likedCount": 0
  },
  {
    "id": "r3008",
    "title": "念奴娇·赤壁怀古",
    "content": [
      "大江东去，浪淘尽，千古风流人物。",
      "故垒西边，人道是，三国周郎赤壁。",
      "乱石穿空，惊涛拍岸，卷起千堆雪。",
      "江山如画，一时多少豪杰。",
      "遥想公瑾当年，小乔初嫁了，雄姿英发。",
      "羽扇纶巾，谈笑间，樯橹灰飞烟灭。",
      "故国神游，多情应笑我，早生华发。",
      "人生如梦，一尊还酹江月。"
    ],
    "poet": "苏轼",
    "dynasty": "宋代",
    "theme": ["励志", "山水"],
    "likedCount": 0
  },
  {
    "id": "r3009",
    "title": "江城子·乙卯正月二十日夜记梦",
    "content": [
      "十年生死两茫茫，不思量，自难忘。",
      "千里孤坟，无处话凄凉。",
      "纵使相逢应不识，尘满面，鬓如霜。",
      "夜来幽梦忽还乡，小轩窗，正梳妆。",
      "相顾无言，惟有泪千行。",
      "料得年年肠断处，明月夜，短松冈。"
    ],
    "poet": "苏轼",
    "dynasty": "宋代",
    "theme": ["爱情", "离别"],
    "likedCount": 0
  },
  {
    "id": "r3010",
    "title": "青玉案·元夕",
    "content": [
      "东风夜放花千树，更吹落、星如雨。",
      "宝马雕车香满路，凤箫声动，玉壶光转，一夜鱼龙舞。",
      "蛾儿雪柳黄金缕，笑语盈盈暗香去。",
      "众里寻他千百度，蓦然回首，那人却在，灯火阑珊处。"
    ],
    "poet": "辛弃疾",
    "dynasty": "宋代",
    "theme": ["爱情", "山水"],
    "likedCount": 0
  },
  {
    "id": "r3011",
    "title": "破阵子·为陈同甫赋壮词以寄之",
    "content": [
      "醉里挑灯看剑，梦回吹角连营。",
      "八百里分麾下炙，五十弦翻塞外声，沙场秋点兵。",
      "马作的卢飞快，弓如霹雳弦惊。",
      "了却君王天下事，赢得生前身后名。可怜白发生。"
    ],
    "poet": "辛弃疾",
    "dynasty": "宋代",
    "theme": ["励志", "离别"],
    "likedCount": 0
  },
  {
    "id": "r3012",
    "title": "声声慢·寻寻觅觅",
    "content": [
      "寻寻觅觅，冷冷清清，凄凄惨惨戚戚。",
      "乍暖还寒时候，最难将息。",
      "三杯两盏淡酒，怎敌他，晚来风急。",
      "雁过也，正伤心，却是旧时相识。",
      "满地黄花堆积。憔悴损，如今有谁堪摘？",
      "守著窗儿，独自怎生得黑？",
      "梧桐更兼细雨，到黄昏、点点滴滴。",
      "这次第，怎一个愁字了得！"
    ],
    "poet": "李清照",
    "dynasty": "宋代",
    "theme": ["爱情", "离别"],
    "likedCount": 0
  },
  {
    "id": "r3013",
    "title": "如梦令·昨夜雨疏风骤",
    "content": [
      "昨夜雨疏风骤，浓睡不消残酒。",
      "试问卷帘人，却道海棠依旧。",
      "知否？知否？应是绿肥红瘦。"
    ],
    "poet": "李清照",
    "dynasty": "宋代",
    "theme": ["爱情"],
    "likedCount": 0
  },
  {
    "id": "r3014",
    "title": "渔家傲·塞下秋来风景异",
    "content": [
      "塞下秋来风景异，衡阳雁去无留意。",
      "四面边声连角起，千嶂里，长烟落日孤城闭。",
      "浊酒一杯家万里，燕然未勒归无计。",
      "羌管悠悠霜满地。人不寐，将军白发征夫泪。"
    ],
    "poet": "范仲淹",
    "dynasty": "宋代",
    "theme": ["山水", "离别"],
    "likedCount": 0
  },
  {
    "id": "r3015",
    "title": "早春呈水部张十八员外",
    "content": [
      "天街小雨润如酥，草色遥看近却无。",
      "最是一年春好处，绝胜烟柳满皇都。"
    ],
    "poet": "韩愈",
    "dynasty": "唐代",
    "theme": ["山水", "励志"],
    "likedCount": 0
  },
  {
    "id": "r3016",
    "title": "山居秋暝",
    "content": [
      "空山新雨后，天气晚来秋。",
      "明月松间照，清泉石上流。",
      "竹喧归浣女，莲动下渔舟。",
      "随意春芳歇，王孙自可留。"
    ],
    "poet": "王维",
    "dynasty": "唐代",
    "theme": ["山水"],
    "likedCount": 0
  },
  {
    "id": "r3017",
    "title": "送元二使安西",
    "content": [
      "渭城朝雨浥轻尘，客舍青青柳色新。",
      "劝君更尽一杯酒，西出阳关无故人。"
    ],
    "poet": "王维",
    "dynasty": "唐代",
    "theme": ["离别", "友情"],
    "likedCount": 0
  },
  {
    "id": "r3018",
    "title": "相思",
    "content": [
      "红豆生南国，春来发几枝。",
      "愿君多采撷，此物最相思。"
    ],
    "poet": "王维",
    "dynasty": "唐代",
    "theme": ["爱情", "思乡"],
    "likedCount": 0
  },
  {
    "id": "r3019",
    "title": "关山月",
    "content": [
      "明月出天山，苍茫云海间。",
      "长风几万里，吹度玉门关。",
      "汉下白登道，胡窥青海湾。",
      "由来征战地，不见有人还。",
      "戍客望边色，思归多苦颜。",
      "高楼当此夜，叹息未应闲。"
    ],
    "poet": "李白",
    "dynasty": "唐代",
    "theme": ["山水", "离别"],
    "likedCount": 0
  },
  {
    "id": "r3020",
    "title": "观沧海",
    "content": [
      "东临碣石，以观沧海。",
      "水何澹澹，山岛竦峙。",
      "树木丛生，百草丰茂。",
      "秋风萧瑟，洪波涌起。",
      "日月之行，若出其中；",
      "星汉灿烂，若出其里。",
      "幸甚至哉，歌以咏志。"
    ],
    "poet": "曹操",
    "dynasty": "汉末",
    "theme": ["山水", "励志"],
    "likedCount": 0
  }
]

